cryspy/__init__.py
cryspy/__main__.py
cryspy/A_functions_base/charge_form_factor.py
cryspy/A_functions_base/database.pickle
cryspy/A_functions_base/database.py
cryspy/A_functions_base/debye_waller_factor.py
cryspy/A_functions_base/extinction.py
cryspy/A_functions_base/flip_ratio.py
cryspy/A_functions_base/function_1_algebra.py
cryspy/A_functions_base/function_1_atomic_vibrations.py
cryspy/A_functions_base/function_1_error_simplex.py
cryspy/A_functions_base/function_1_gamma_nu.py
cryspy/A_functions_base/function_1_inversed_hessian.py
cryspy/A_functions_base/function_1_magnetic.py
cryspy/A_functions_base/function_1_markdown.py
cryspy/A_functions_base/function_1_matrices.py
cryspy/A_functions_base/function_1_objects.py
cryspy/A_functions_base/function_1_roots.py
cryspy/A_functions_base/function_1_scat_length_neutron.py
cryspy/A_functions_base/function_1_strings.py
cryspy/A_functions_base/function_2_crystallography_base.py
cryspy/A_functions_base/function_2_mem.py
cryspy/A_functions_base/function_2_space_group.py
cryspy/A_functions_base/function_2_sym_elems.py
cryspy/A_functions_base/function_3_den_file.py
cryspy/A_functions_base/function_3_extinction.py
cryspy/A_functions_base/function_3_mcif.py
cryspy/A_functions_base/function_4_flip_ratio.py
cryspy/A_functions_base/integrated_intensity_powder_diffraction.py
cryspy/A_functions_base/itables.txt
cryspy/A_functions_base/local_susceptibility.py
cryspy/A_functions_base/magnetic_data.txt
cryspy/A_functions_base/magnetic_form_factor.py
cryspy/A_functions_base/magnetic_table_bns.txt
cryspy/A_functions_base/matrix_operations.py
cryspy/A_functions_base/mempy.py
cryspy/A_functions_base/orbital_functions.py
cryspy/A_functions_base/powder_diffraction_const_wavelength.py
cryspy/A_functions_base/powder_diffraction_tof.py
cryspy/A_functions_base/powder_diffraction_tof_zcode.py
cryspy/A_functions_base/preferred_orientation.py
cryspy/A_functions_base/structure_factor.py
cryspy/A_functions_base/symmetry_constraints.py
cryspy-0.10.0.dist-info/licenses/AUTHORS
cryspy-0.10.0.dist-info/licenses/LICENSE
cryspy-0.10.0.dist-info/METADATA
cryspy-0.10.0.dist-info/WHEEL
cryspy-0.10.0.dist-info/top_level.txt
cryspy-0.10.0.dist-info/RECORD
