Metadata-Version: 2.4
Name: cryspy
Version: 0.10.0
Summary: PNPD data analysis
Home-page: https://github.com/ikibalin/cryspy
Author: Iurii Kibalin
Author-email: yurikibalin@outlook.com
License: MIT License
Keywords: Polarized Neutron Diffraction Data Analysis
Classifier: Programming Language :: Python :: 3
Classifier: Programming Language :: Python :: 3.5
Classifier: Programming Language :: Python :: 3.6
Classifier: Programming Language :: Python :: 3.7
Classifier: Programming Language :: Python :: 3.8
Classifier: Programming Language :: Python :: 3.9
Classifier: Programming Language :: Python :: 3.10
Classifier: Programming Language :: Python :: 3.11
Classifier: Programming Language :: Python :: 3.12
Classifier: Programming Language :: Python :: 3.13
Classifier: Operating System :: OS Independent
License-File: LICENSE
License-File: AUTHORS
Requires-Dist: numpy
Requires-Dist: scipy
Requires-Dist: pycifstar
Requires-Dist: matplotlib
Dynamic: author
Dynamic: author-email
Dynamic: classifier
Dynamic: description
Dynamic: home-page
Dynamic: keywords
Dynamic: license
Dynamic: license-file
Dynamic: requires-dist
Dynamic: summary
